README.txt
setup.py
docs/HISTORY.txt
docs/LICENSE.GPL
docs/LICENSE.txt
docs/config.xml
docs/defaultAvatar.png
qi/__init__.py
qi.xmpp.botfarm.egg-info/PKG-INFO
qi.xmpp.botfarm.egg-info/SOURCES.txt
qi.xmpp.botfarm.egg-info/dependency_links.txt
qi.xmpp.botfarm.egg-info/entry_points.txt
qi.xmpp.botfarm.egg-info/namespace_packages.txt
qi.xmpp.botfarm.egg-info/not-zip-safe
qi.xmpp.botfarm.egg-info/paster_plugins.txt
qi.xmpp.botfarm.egg-info/requires.txt
qi.xmpp.botfarm.egg-info/top_level.txt
qi/xmpp/__init__.py
qi/xmpp/botfarm/__init__.py
qi/xmpp/botfarm/config.py
qi/xmpp/botfarm/logutil.py
qi/xmpp/botfarm/main.py
qi/xmpp/botfarm/session.py
qi/xmpp/botfarm/sessionManager.py
qi/xmpp/botfarm/xmlConfig.py
qi/xmpp/botfarm/xmlrpc.py