Metadata-Version: 1.0
Name: qi.xmpp.botfarm
Version: 0.1
Summary: A twisted server supporting multiple xmpp helpdesk bots.
Home-page: http://chatblox.com
Author: G. Gozadinos
Author-email: ggozad@qiweb.net
License: GPL
Keywords: xmpp twisted bot jabber helpdesk
Platform: UNKNOWN
Classifier: Programming Language :: Python
Classifier: Topic :: Software Development :: Libraries :: Python Modules
